LICENSE
README.md
setup.py
cimetrics/__init__.py
cimetrics/env.py
cimetrics/github_pr.py
cimetrics/plot.py
cimetrics/stack.py
cimetrics/upload.py
cimetrics/upload_complete.py
cimetrics.egg-info/PKG-INFO
cimetrics.egg-info/SOURCES.txt
cimetrics.egg-info/dependency_links.txt
cimetrics.egg-info/requires.txt
cimetrics.egg-info/top_level.txt